pulse/__init__.py
pulse/auth.py
pulse/config.py
pulse/debug.py
pulse/dsl.py
pulse/py.typed
pulse/starters.py
pulse/analysis/__init__.py
pulse/analysis/analyzer.py
pulse/analysis/processes.py
pulse/analysis/results.py
pulse/core/__init__.py
pulse/core/batching.py
pulse/core/client.py
pulse/core/exceptions.py
pulse/core/gzip_client.py
pulse/core/jobs.py
pulse/core/models.py
pulse/core/retry.py
pulse/core/utils.py
pulse/core/validation.py
pulse_sdk-0.5.0.dist-info/licenses/LICENSE
pulse_sdk-0.5.0.dist-info/licenses/LICENSE-MANIFEST.json
pulse_sdk-0.5.0.dist-info/licenses/NOTICE
pulse_sdk-0.5.0.dist-info/METADATA
pulse_sdk-0.5.0.dist-info/WHEEL
pulse_sdk-0.5.0.dist-info/top_level.txt
pulse_sdk-0.5.0.dist-info/RECORD
