Metadata-Version: 2.4
Name: pulse-sdk
Version: 0.5.0
Summary: Idiomatic, type-safe Python client for the Pulse REST API
Author-email: Researchwise AI <support@researchwiseai.com>
Maintainer-email: Researchwise AI <support@researchwiseai.com>
License-Expression: Apache-2.0
Project-URL: Homepage, https://github.com/researchwiseai/pulse-py#readme
Project-URL: Repository, https://github.com/researchwiseai/pulse-py
Project-URL: Documentation, https://researchwiseai.github.io/pulse-py/
Project-URL: Changelog, https://github.com/researchwiseai/pulse-py/blob/main/CHANGELOG.md
Project-URL: Bug Tracker, https://github.com/researchwiseai/pulse-py/issues
Project-URL: Security Policy, https://github.com/researchwiseai/pulse-py/blob/main/SECURITY.md
Project-URL: Release Notes, https://github.com/researchwiseai/pulse-py/releases
Keywords: ai,nlp,text-analysis,machine-learning,api-client,sentiment-analysis,embeddings,clustering,summarization,theme-analysis,similarity,data-science,research
Classifier: Development Status :: 5 - Production/Stable
Classifier: Intended Audience :: Developers
Classifier: Intended Audience :: Science/Research
Classifier: Intended Audience :: Information Technology
Classifier: Intended Audience :: Education
Classifier: Operating System :: OS Independent
Classifier: Operating System :: POSIX
Classifier: Operating System :: Microsoft :: Windows
Classifier: Operating System :: MacOS
Classifier: Programming Language :: Python :: 3.8
Classifier: Programming Language :: Python :: 3.9
Classifier: Programming Language :: Python :: 3.10
Classifier: Programming Language :: Python :: 3.11
Classifier: Programming Language :: Python :: 3.12
Classifier: Programming Language :: Python :: 3.13
Classifier: Topic :: Scientific/Engineering :: Artificial Intelligence
Classifier: Topic :: Scientific/Engineering :: Information Analysis
Classifier: Topic :: Software Development :: Libraries :: Python Modules
Classifier: Topic :: Text Processing :: Linguistic
Classifier: Topic :: Text Processing :: General
Classifier: Topic :: Internet :: WWW/HTTP :: Dynamic Content
Classifier: Topic :: Utilities
Classifier: Environment :: Console
Classifier: Environment :: Web Environment
Classifier: Natural Language :: English
Classifier: Typing :: Typed
Requires-Python: >=3.8
License-File: LICENSE
License-File: LICENSE-MANIFEST.json
License-File: NOTICE
Requires-Dist: httpx>=0.24.0
Requires-Dist: pydantic<3.0,>=2.0
Requires-Dist: typing-extensions>=4.0
Provides-Extra: analysis
Requires-Dist: numpy>=1.21.0; extra == "analysis"
Requires-Dist: pandas>=1.3.0; extra == "analysis"
Requires-Dist: scikit-learn>=1.4; extra == "analysis"
Provides-Extra: visualization
Requires-Dist: matplotlib>=3.5.0; extra == "visualization"
Requires-Dist: seaborn>=0.11.0; extra == "visualization"
Provides-Extra: nlp
Requires-Dist: textblob>=0.17.0; extra == "nlp"
Provides-Extra: caching
Requires-Dist: diskcache>=5.4.0; extra == "caching"
Provides-Extra: progress
Requires-Dist: tqdm>=4.64.0; extra == "progress"
Provides-Extra: all
Requires-Dist: pulse-sdk[analysis,caching,nlp,progress,visualization]; extra == "all"
Provides-Extra: minimal
Provides-Extra: dev
Requires-Dist: pytest>=6.0; extra == "dev"
Requires-Dist: pytest-mock>=3.6.0; extra == "dev"
Requires-Dist: pytest-vcr>=1.0.0; extra == "dev"
Requires-Dist: pytest-cov>=4.0.0; extra == "dev"
Requires-Dist: pytest-timeout>=2.0.0; extra == "dev"
Requires-Dist: black==25.1.0; extra == "dev"
Requires-Dist: nbqa>=1.6.0; extra == "dev"
Requires-Dist: ruff>=0.1.0; extra == "dev"
Requires-Dist: pre-commit>=2.9.2; extra == "dev"
Requires-Dist: bandit[sarif,toml]>=1.8.0; extra == "dev"
Requires-Dist: pip-audit>=2.6.0; extra == "dev"
Requires-Dist: mkdocs>=1.4.0; extra == "dev"
Requires-Dist: mkdocs-material>=8.0.0; extra == "dev"
Requires-Dist: requests>=2.25.0; extra == "dev"
Requires-Dist: markdown>=3.3.0; extra == "dev"
Requires-Dist: semver>=3.0.0; extra == "dev"
Requires-Dist: build>=0.10.0; extra == "dev"
Requires-Dist: twine>=4.0.0; extra == "dev"
Dynamic: license-file
